.hgtags
COPYING.LESSER
MANIFEST.in
README
python-pyxst.spec
setup.py
tox.ini
pyxst/__init__.py
pyxst.egg-info/PKG-INFO
pyxst.egg-info/SOURCES.txt
pyxst.egg-info/dependency_links.txt
pyxst.egg-info/requires.txt
pyxst.egg-info/top_level.txt
pyxst/dtd/__init__.py
pyxst/dtd/constants.py
pyxst/dtd/errors.py
pyxst/dtd/groups.py
pyxst/dtd/nodes.py
pyxst/dtd/parser.py
pyxst/dtd/root.py
pyxst/dtd/utils.py
pyxst/xml_struct/__init__.py
pyxst/xml_struct/comparator.py
pyxst/xml_struct/docs_analyzer.py
pyxst/xml_struct/graph.py
pyxst/xml_struct/graph_nodes.py
pyxst/xml_struct/graph_target_relations.py
pyxst/xml_struct/pprint.py
pyxst/xml_struct/utils.py
pyxst/xsd/__init__.py
pyxst/xsd/attributes.py
pyxst/xsd/constraints.py
pyxst/xsd/elements.py
pyxst/xsd/errors.py
pyxst/xsd/groups.py
pyxst/xsd/parser.py
pyxst/xsd/root.py
pyxst/xsd/types.py
pyxst/xsd/utils.py