Metadata-Version: 2.1
Name: pyxst
Version: 0.3.2
Summary: XML Schema Tools for Python
Home-page: https://www.logilab.org/project/pyxst
Author: Logilab
Author-email: devel@logilab.fr
License: LGPL
Platform: UNKNOWN
